{
  "kind": "collectionType",
  "collectionName": "orders",
  "info": {
    "singularName": "order",
    "pluralName": "orders",
    "displayName": "Order",
    "description": ""
  },
  "options": {
    "draftAndPublish": true
  },
  "pluginOptions": {},
  "attributes": {
    "stripeSessionId": {
      "type": "string"
    },
    "products": {
      "type": "json"
    },
    "email": {
      "type": "email"
    },
    "billingAddress": {
      "type": "json"
    },
    "shippingAddress": {
      "type": "json"
    },
    "phone_number": {
      "type": "string"
    }
  }
}
